basex/__init__.py
basex/_version.py
basex/basex.py
basexpy-0.1.0.dist-info/LICENSE
basexpy-0.1.0.dist-info/METADATA
basexpy-0.1.0.dist-info/WHEEL
basexpy-0.1.0.dist-info/top_level.txt
basexpy-0.1.0.dist-info/RECORD
